akashshare/__main__.py
akashshare/lib/__init__.py
akashshare/lib/discovery.py
akashshare/lib/file_ops.py
akashshare/lib/main.py
akashshare/lib/receiver.py
akashshare/lib/sender.py
akashshare/utils/__init__.py
akashshare/utils/global_vars.py
akashshare/utils/helper.py
akashshare-0.1.7.dist-info/METADATA
akashshare-0.1.7.dist-info/WHEEL
akashshare-0.1.7.dist-info/entry_points.txt
akashshare-0.1.7.dist-info/top_level.txt
akashshare-0.1.7.dist-info/RECORD
