Metadata-Version: 2.4
Name: akashshare
Version: 0.1.7
Summary: CLI tool to share files over LAN using UDP + TCP
Author-email: Akash <akashpawar202k@gmail.com>
License: MIT
Requires-Python: >=3.8
Requires-Dist: InquirerPy
Requires-Dist: tqdm
